setup.py
Lev_Distributions/Binomialdistribution.py
Lev_Distributions/Gaussiandistribution.py
Lev_Distributions/Generaldistribution.py
Lev_Distributions/__init__.py
Lev_Distributions.egg-info/PKG-INFO
Lev_Distributions.egg-info/SOURCES.txt
Lev_Distributions.egg-info/dependency_links.txt
Lev_Distributions.egg-info/not-zip-safe
Lev_Distributions.egg-info/top_level.txt